cythontools/__init__.py
cythontools/command/__generate_commands.py
cythontools/command/__init__.py
cythontools/command/bdist.py
cythontools/command/bdist_wheel.py
cythontools/command/build.py
cythontools/command/build_ext.py
cythontools/command/build_py.py
cythontools/command/clean.py
cythontools/command/command.py
cythontools/command/egg_info.py
cythontools/command/generate_source_manifest.py
cythontools/command/install.py
cythontools/command/install_lib.py
cythontools/command/install_scripts.py
cythontools/command/sdist.py
cythontools/command/test.py
cythontools-0.0.0.4.dist-info/METADATA
cythontools-0.0.0.4.dist-info/WHEEL
cythontools-0.0.0.4.dist-info/top_level.txt
cythontools-0.0.0.4.dist-info/RECORD
