Metadata-Version: 2.1
Name: cythontools
Version: 0.0.0.4
Summary: Tools for building and testing Cython projects
Home-page: UNKNOWN
Author: Jeremiah Blanchard
Author-email: jjb@eng.ufl.edu
License: GPL 3
Platform: UNKNOWN
